autorun_inf_deobfuscator/__init__.py
autorun_inf_deobfuscator/cli_script.py
autorun_inf_deobfuscator-1.0.1.dist-info/LICENSE
autorun_inf_deobfuscator-1.0.1.dist-info/METADATA
autorun_inf_deobfuscator-1.0.1.dist-info/WHEEL
autorun_inf_deobfuscator-1.0.1.dist-info/entry_points.txt
autorun_inf_deobfuscator-1.0.1.dist-info/top_level.txt
autorun_inf_deobfuscator-1.0.1.dist-info/RECORD
