Metadata-Version: 2.1
Name: autorun-inf-deobfuscator
Version: 1.0.1
Summary: A cli script to deobfuscate obfuscated autorun.inf files as used by the Conficker / Downadup malware for example.
Home-page: https://github.com/wahlflo/AurorunInfDeobfuscator
Author: Florian Wahl
Author-email: florian.wahl.developer@gmail.com
Classifier: Programming Language :: Python :: 3
Classifier: License :: OSI Approved :: MIT License
Classifier: Operating System :: OS Independent
License-File: LICENSE
Requires-Dist: cli-formatter (>=1.2.0)
